dauthz/__init__.py
dauthz/apps.py
dauthz/core.py
dauthz/settings.py
dauthz/utils.py
dauthz/adapters/__init__.py
dauthz/backends/__init__.py
dauthz/backends/casbin_backend.py
dauthz/decorators/__init__.py
dauthz/decorators/_enforcer_decorator.py
dauthz/decorators/_request_decorator.py
dauthz/management/__init__.py
dauthz/management/commands/__init__.py
dauthz/management/commands/group.py
dauthz/management/commands/policy.py
dauthz/management/commands/role.py
dauthz/management/commands/utils.py
dauthz/middlewares/__init__.py
dauthz/middlewares/enforcer_middleware.py
dauthz/middlewares/request_middleware.py
dauthz/migrations/__init__.py
node_modules/npm/node_modules/node-gyp/gyp/gyp_main.py
node_modules/npm/node_modules/node-gyp/gyp/test_gyp.py
node_modules/npm/node_modules/node-gyp/gyp/pylib/gyp/MSVSNew.py
node_modules/npm/node_modules/node-gyp/gyp/pylib/gyp/MSVSProject.py
node_modules/npm/node_modules/node-gyp/gyp/pylib/gyp/MSVSSettings.py
node_modules/npm/node_modules/node-gyp/gyp/pylib/gyp/MSVSSettings_test.py
node_modules/npm/node_modules/node-gyp/gyp/pylib/gyp/MSVSToolFile.py
node_modules/npm/node_modules/node-gyp/gyp/pylib/gyp/MSVSUserFile.py
node_modules/npm/node_modules/node-gyp/gyp/pylib/gyp/MSVSUtil.py
node_modules/npm/node_modules/node-gyp/gyp/pylib/gyp/MSVSVersion.py
node_modules/npm/node_modules/node-gyp/gyp/pylib/gyp/__init__.py
node_modules/npm/node_modules/node-gyp/gyp/pylib/gyp/common.py
node_modules/npm/node_modules/node-gyp/gyp/pylib/gyp/common_test.py
node_modules/npm/node_modules/node-gyp/gyp/pylib/gyp/easy_xml.py
node_modules/npm/node_modules/node-gyp/gyp/pylib/gyp/easy_xml_test.py
node_modules/npm/node_modules/node-gyp/gyp/pylib/gyp/flock_tool.py
node_modules/npm/node_modules/node-gyp/gyp/pylib/gyp/input.py
node_modules/npm/node_modules/node-gyp/gyp/pylib/gyp/input_test.py
node_modules/npm/node_modules/node-gyp/gyp/pylib/gyp/mac_tool.py
node_modules/npm/node_modules/node-gyp/gyp/pylib/gyp/msvs_emulation.py
django_authorization-1.4.0.dist-info/LICENSE
django_authorization-1.4.0.dist-info/METADATA
django_authorization-1.4.0.dist-info/WHEEL
django_authorization-1.4.0.dist-info/top_level.txt
django_authorization-1.4.0.dist-info/RECORD
