Metadata-Version: 2.1
Name: django-authorization
Version: 1.4.0
Summary: An authorization library that supports access control models like ACL, RBAC, ABAC in Django
Author-email: JonLee <leeqvip@gmail.com>
License: Apache 2.0
Project-URL: Home-page, https://github.com/pycasbin/django-authorization
Keywords: casbin,django,acl,rbac,abac,auth,authz,authorization,access control,permission
Classifier: Programming Language :: Python :: 3.6
Classifier: Programming Language :: Python :: 3.7
Classifier: Programming Language :: Python :: 3.8
Classifier: Programming Language :: Python :: 3.9
Classifier: Programming Language :: Python :: 3.10
Classifier: License :: OSI Approved :: Apache Software License
Classifier: Operating System :: OS Independent
Requires-Python: >=3.6
License-File: LICENSE
Requires-Dist: casbin >=1.17.0
Requires-Dist: Django >=3.0.0
